{

  "introduction" : [
    {
      "heading_El": "기업철학",
      "d_title": "좋은 친구 같은 기업, <br/> BGF <br/> Be Good Friends!",
      "d_data": "BGF는 Be Good Friends의 줄임말로 '좋은 친구'같은 기업이 되겠다는 의미를 담고 있습니다. 고객은 물론 지역 사회에 대한 역할과 책임을 다하는 BGF는 변화와 위기에 맞서 끊임없이 혁신중입니다. 또한 소매 유통을 넘어 제조, 물류, 금융서비스 등 모든 사업부문의 가치를 유기적으로 연결하여 시너지를 발휘하는 기업으로 성장하기 위해 노력하고 있습니다.",
      "anchor": "BGF의 기업철학 알아보기",
      "anchor_addr": "./sub1/sub1_1.html",
      "map": "./images/introduction1.jpg"
    },
    {
      "heading_El": "기업비전",
      "d_title": "BGF리테일에는 <br/> 5가지의 <br/> 핵심가치가 있습니다.",
      "d_data": "BGF리테일은 Be Good Friends에서 연유한 이름으로 고객, 가맹점주, 지역사회에 좋은 친구 같은 기업이 되겠다는 의미를 담고 있습니다. 긍정에너지 열정! 편리한 세상을 위한 도전! 꾸밈없이 당당한 정직! 서로에게 든든한 팀웍! 다른 내일을 위한 학습! BGF의 경영이념은 언제 어디서나 최상의 상품과 서비스를 제공하여 고객가치를 실현하고 사회발전에 공헌하는 기업으로 성장하는 것 입니다.",
      "anchor": "BGF의 기업비전 알아보기",
      "anchor_addr": "./sub1/sub1_2.html",
      "map": "./images/introduction2.jpg"
    },
    {
      "heading_El": "복리후생",
      "d_title": "새로운 것에 대한 <br/> 학습과 성장. <br/> BGF리테일이 함께합니다.",
      "d_data": "급변하는 환경에서 더 나은 상품과 서비스를 제공하는 친구가 되기 위해 BGF는 언제나 학습합니다. 업계에서 가장 숙련된 노하우를 보유하고 있는 BGF는 구성원 각자가 자신의 역할을 충분히 수행할 수 있도록 체계적인 교육을 운영하고 있습니다. 특히, BGF리테일의 새로운 친구가 된 신입사원에게는 조직과 업무에 잘 적응할 수 있도록 1년 간의 밀착 교육 제도를 제공하고 있습니다.",
      "anchor": "BGF의 복리후생 알아보기",
      "anchor_addr": "./sub6/sub6_2.html",
      "map": "./images/introduction3.jpg"
    }
  ]

}